Workbook

Sheet Test Credentials
A1: Role | B1: Email | C1: Password | D1: Distributor | E1: Notes
A2: SUPER_ADMIN | B2: admin@mygaslink.com | C2: Admin@123 | D2: All (Platform) | E2: Full platform access, select distributor via header
A3: DISTRIBUTOR_ADMIN (Non-GST) | B3: bhargava@gasagency.com | C3: Distadmin@123 | D3: Bhargava Gas Agency (Hyderabad) | E3: GST disabled, dist-001
A4: FINANCE | B4: finance@gasagency.com | C4: Finance@123 | D4: Bhargava Gas Agency | E4: Billing & payment operations
A5: INVENTORY | B5: inventory@gasagency.com | C5: Inventory@123 | D5: Bhargava Gas Agency | E5: Stock & warehouse operations
A6: DISTRIBUTOR_ADMIN (GST) | B6: sharma@gasdist.com | C6: Gstadmin@123 | D6: Sharma Gas Distributors (Bangalore) | E6: GST sandbox mode, dist-002
A7: DRIVER | B7: (Check drivers list) | C7: (Set via seed) | D7: Bhargava Gas Agency | E7: 3 drivers: Raju Kumar, Suresh Babu, Venkat Rao
A8: CUSTOMER | B8: (Provision via Portal Access) | C8: (Set during provisioning) | D8: Bhargava Gas Agency | E8: 5 customers: Royal Kitchen, Spice Garden, Metropolis, Lakshmi Mess, Green Valley

Sheet Role-Based Access
A1: Test ID | B1: Role | C1: Page/Feature | D1: Action | E1: Expected Result | F1: Pass/Fail | G1: Actual Result | H1: Notes
A2: RA-001 | B2: SUPER_ADMIN | C2: Login | D2: Login with admin@mygaslink.com | E2: Successful login, dashboard shown
A3: RA-002 | B3: SUPER_ADMIN | C3: Dashboard/Analytics | D3: /app/analytics | E3: KPIs and pending actions load
A4: RA-003 | B4: SUPER_ADMIN | C4: Orders | D4: /app/orders | E4: Full CRUD access
A5: RA-004 | B5: SUPER_ADMIN | C5: Customers | D5: /app/customers | E5: Full CRUD access
A6: RA-005 | B6: SUPER_ADMIN | C6: Inventory | D6: /app/inventory | E6: All tabs accessible
A7: RA-006 | B7: SUPER_ADMIN | C7: Fleet | D7: /app/fleet | E7: Full access - drivers, vehicles, assignments
A8: RA-007 | B8: SUPER_ADMIN | C8: Billing & Payments | D8: /app/billing-payments | E8: Full access
A9: RA-008 | B9: SUPER_ADMIN | C9: Settings - All Tabs | D9: Click each tab | E9: All tabs visible and functional
A10: RA-009 | B10: SUPER_ADMIN | C10: Distributors | D10: /app/distributors | E10: Distributor CRUD
A11: RA-010 | B11: SUPER_ADMIN | C11: Collections | D11: /app/collections | E11: Collections dashboard loads
A12: RA-011 | B12: SUPER_ADMIN | C12: Provider Catalog | D12: /app/provider-catalog | E12: Catalog page loads
A13: RA-012 | B13: SUPER_ADMIN | C13: Health Monitor | D13: /app/health | E13: Health page loads
... A53: RA-052 | B53: CUSTOMER | C53: Other Customer Data | D53: API for other customer ID | E53: Forbidden
A55: Total Tests | B55: =COUNTA(F2:F54)
A56: PASS | B56: =COUNTIF(F2:F54,"PASS")
A57: FAIL | B57: =COUNTIF(F2:F54,"FAIL")
A58: BLOCKED | B58: =COUNTIF(F2:F54,"BLOCKED")
A59: SKIPPED | B59: =COUNTIF(F2:F54,"SKIPPED")
A60: NOT TESTED | B60: =COUNTIF(F2:F54,"NOT TESTED")
A61: Pass Rate | B61: =IF(B56>0,B56/B55,0)

Sheet Orders Tests
A1: Test ID | B1: Test Case | C1: Precondition | D1: Steps | E1: Expected Result | F1: Pass/Fail | G1: Actual Result | H1: Notes
A2: FO-001 | B2: Create order - single item | C2: Admin, customers exist | D2: Create Order > Customer > Tomorrow > 19KG x 5 > Submit | E2: Status=pending_driver_assignment
A3: FO-002 | B3: Create order - multiple items | C3: Admin | D3: Create > 19KG x 3 + 47.5KG x 2 > Submit | E3: 2 line items, total correct
A4: FO-003 | B4: Create order - no customer | C4: Admin | D4: Create > Skip customer > Submit | E4: Validation: customer required
A5: FO-004 | B5: Create order - no items | C5: Admin | D5: Create > Customer > Submit empty | E5: Validation: items required
A6: FO-005 | B6: Create order - past date | C6: Admin | D6: Create > Yesterday date > Submit | E6: Validation: past date
A7: FO-006 | B7: Create order - stopped customer | C7: Supply stopped | D7: Create for stopped customer | E7: Error: supply stopped
A8: FO-007 | B8: Edit order - change date | C8: Pending order | D8: Edit > Change date > Save | E8: Date updated
A9: FO-008 | B9: Edit order - modify items | C9: Pending order | D9: Edit > Add/remove items > Save | E9: Items updated, total recalculated
A10: FO-009 | B10: Edit delivered order | C10: Delivered order | D10: Try to edit | E10: Edit hidden/disabled
A11: FO-010 | B11: Assign driver | C11: Pending_driver_assignment | D11: Assign > Driver + Vehicle > Confirm | E11: Status=pending_dispatch
A12: FO-011 | B12: Bulk assign driver | C12: 3+ pending orders | D12: Select > Bulk Assign > Driver+Vehicle | E12: All assigned
A13: FO-012 | B13: Cancel before dispatch | C13: Pending order | D13: Cancel > Confirm | E13: Cancelled, no invoice
... A23: FO-022 | B23: Search by keyword | C23: Known order# | D23: Type in search | E23: Match found
A25: Total Tests | B25: =COUNTA(F2:F24)
A26: PASS | B26: =COUNTIF(F2:F24,"PASS")
A27: FAIL | B27: =COUNTIF(F2:F24,"FAIL")
A28: BLOCKED | B28: =COUNTIF(F2:F24,"BLOCKED")
A29: SKIPPED | B29: =COUNTIF(F2:F24,"SKIPPED")
A30: NOT TESTED | B30: =COUNTIF(F2:F24,"NOT TESTED")
A31: Pass Rate | B31: =IF(B26>0,B26/B25,0)

Sheet Inventory Tests
A1: Test ID | B1: Test Case | C1: Precondition | D1: Steps | E1: Expected Result | F1: Pass/Fail | G1: Actual Result | H1: Notes
A2: FI-001 | B2: View daily summary | C2: Inventory/Admin | D2: Inventory > Daily Summary | E2: All cylinder types with balances
A3: FI-002 | B3: Navigate dates | C3: On summary | D3: Prev/Next/Today buttons | E3: Date changes, data refreshes
A4: FI-003 | B4: Record incoming fulls | C4: Day unlocked | D4: +Incoming > Qty=50, doc, vehicle > Submit | E4: Balance increases
A5: FI-004 | B5: Record outgoing empties | C5: Day unlocked | D5: +Outgoing > Qty=30, doc > Submit | E5: Recorded
A6: FI-005 | B6: Manual adjustment | C6: Day unlocked | D6: Adjustment > Type, qty, reason > Submit | E6: Pending approval
A7: FI-006 | B7: Lock day | C7: Admin, unlocked | D7: Lock > Confirm | E7: Buttons disabled
A8: FI-007 | B8: Unlock day | C8: Locked day | D8: Unlock > Confirm | E8: Buttons re-enabled
A9: FI-008 | B9: Add on locked day | C9: Day locked | D9: Try incoming fulls | E9: Blocked
A10: FI-009 | B10: Depot history | C10: Movements exist | D10: Depot History > Filters | E10: Filtered history
A11: FI-010 | B11: View cancelled stock | C11: Partial deliveries | D11: Cancelled Stock tab | E11: Items with status
A12: FI-011 | B12: Return cancelled stock | C12: Stock on vehicle | D12: Return > Confirm | E12: returned_to_depot
A13: FI-012 | B13: View forecast | C13: History exists | D13: Forecast tab | E13: Stock, demand, days remaining
... A19: FI-018 | B19: Warning alert | C19: Stock < warning | D19: View summary | E19: Warning badge
A21: Total Tests | B21: =COUNTA(F2:F20)
A22: PASS | B22: =COUNTIF(F2:F20,"PASS")
A23: FAIL | B23: =COUNTIF(F2:F20,"FAIL")
A24: BLOCKED | B24: =COUNTIF(F2:F20,"BLOCKED")
A25: SKIPPED | B25: =COUNTIF(F2:F20,"SKIPPED")
A26: NOT TESTED | B26: =COUNTIF(F2:F20,"NOT TESTED")
A27: Pass Rate | B27: =IF(B22>0,B22/B21,0)

Sheet Customer Tests
A1: Test ID | B1: Test Case | C1: Precondition | D1: Steps | E1: Expected Result | F1: Pass/Fail | G1: Actual Result | H1: Notes
A2: FC-001 | B2: Create - all fields | C2: Admin | D2: All fields + contacts + discounts > Submit | E2: Created
A3: FC-002 | B3: Create - min fields | C3: Admin | D3: Name + Phone > Submit | E3: Created
A4: FC-003 | B4: Create - duplicate phone | C4: Phone exists | D4: Same phone > Submit | E4: Error: duplicate
A5: FC-004 | B5: Edit customer | C5: Exists | D5: Edit > Change fields > Save | E5: Updated
A6: FC-005 | B6: Stop supply | C6: Active | D6: Stop Supply > Confirm | E6: Stopped
A7: FC-006 | B7: Resume supply | C7: Stopped | D7: Resume > Confirm | E7: Resumed
A8: FC-007 | B8: Detail - Orders tab | C8: Has orders | D8: View > Orders | E8: Order list
A9: FC-008 | B9: Detail - Invoices tab | C9: Has invoices | D9: View > Invoices | E9: Invoice list
A10: FC-009 | B10: Detail - Payments tab | C10: Has payments | D10: View > Payments | E10: Payment list
A11: FC-010 | B11: Detail - Inventory tab | C11: Has balances | D11: View > Inventory | E11: Balances shown
A12: FC-011 | B12: Detail - Ledger tab | C12: Has transactions | D12: View > Ledger | E12: Running balance
A13: FC-012 | B13: Search by name | C13: Multiple | D13: Type name | E13: Filtered
... A18: FC-017 | B18: Reject modification | C18: Pending | D18: Admin > Reject | E18: Rejected
A20: Total Tests | B20: =COUNTA(F2:F19)
A21: PASS | B21: =COUNTIF(F2:F19,"PASS")
A22: FAIL | B22: =COUNTIF(F2:F19,"FAIL")
A23: BLOCKED | B23: =COUNTIF(F2:F19,"BLOCKED")
A24: SKIPPED | B24: =COUNTIF(F2:F19,"SKIPPED")
A25: NOT TESTED | B25: =COUNTIF(F2:F19,"NOT TESTED")
A26: Pass Rate | B26: =IF(B21>0,B21/B20,0)

Sheet Billing Tests
A1: Test ID | B1: Test Case | C1: Precondition | D1: Steps | E1: Expected Result | F1: Pass/Fail | G1: Actual Result | H1: Notes
A2: FB-001 | B2: View invoices list | C2: Invoices exist | D2: Billing > Invoices | E2: List loads
A3: FB-002 | B3: Filter by status | C3: Various | D3: Status > ISSUED | E3: Filtered
A4: FB-003 | B4: Filter by IRN status | C4: GST invoices | D4: IRN > SUCCESS | E4: Filtered
A5: FB-004 | B5: Filter by date range | C5: Various dates | D5: Set range | E5: Filtered
A6: FB-005 | B6: Invoice detail | C6: Invoice exists | D6: Click invoice | E6: Detail modal
A7: FB-006 | B7: Download PDF | C7: Invoice exists | D7: Download | E7: PDF, content-type=application/pdf
A8: FB-007 | B8: Payment - cash | C8: Outstanding | D8: Pay full > Cash > Submit | E8: Status=paid
A9: FB-008 | B9: Payment - UPI | C9: Outstanding | D9: Pay > UPI > Ref > Submit | E9: Recorded
A10: FB-009 | B10: Payment - bank transfer | C10: Outstanding | D10: Pay > Bank > NEFT ref | E10: Recorded
A11: FB-010 | B11: Payment - cheque | C11: Outstanding | D11: Pay > Cheque > # > Submit | E11: Recorded
A12: FB-011 | B12: Partial payment | C12: Rs.10000 invoice | D12: Pay Rs.5000 | E12: Partially_paid, outstanding=5000
A13: FB-012 | B13: Auto-allocate | C13: Unallocated payment | D13: Auto Allocate | E13: FIFO to oldest invoices
... A27: FB-026 | B27: Mark overdue | C27: Past-due invoices | D27: Trigger overdue | E27: Flagged
A29: Total Tests | B29: =COUNTA(F2:F28)
A30: PASS | B30: =COUNTIF(F2:F28,"PASS")
A31: FAIL | B31: =COUNTIF(F2:F28,"FAIL")
A32: BLOCKED | B32: =COUNTIF(F2:F28,"BLOCKED")
A33: SKIPPED | B33: =COUNTIF(F2:F28,"SKIPPED")
A34: NOT TESTED | B34: =COUNTIF(F2:F28,"NOT TESTED")
A35: Pass Rate | B35: =IF(B30>0,B30/B29,0)

Sheet Fleet Tests
A1: Test ID | B1: Test Case | C1: Precondition | D1: Steps | E1: Expected Result | F1: Pass/Fail | G1: Actual Result | H1: Notes
A2: FF-001 | B2: Create driver | C2: Admin | D2: Add > Name, Phone, Licence > Submit | E2: Created, active
A3: FF-002 | B3: Edit driver | C3: Exists | D3: Edit > Change phone > Save | E3: Updated
A4: FF-003 | B4: Delete driver | C4: No assignments | D4: Delete > Confirm | E4: Deactivated
A5: FF-004 | B5: Toggle availability | C5: Active | D5: Toggle | E5: Badge updates
A6: FF-005 | B6: Create vehicle | C6: Admin | D6: Add > Number, Type, Capacity > Submit | E6: Created
A7: FF-006 | B7: Edit vehicle | C7: Exists | D7: Edit > Capacity > Save | E7: Updated
A8: FF-007 | B8: Delete vehicle | C8: Not in use | D8: Delete > Confirm | E8: Deactivated
A9: FF-008 | B9: Create assignment | C9: Free driver+vehicle | D9: Create > Driver+Vehicle > Submit | E9: dispatch_ready
A10: FF-009 | B10: Update assignment | C10: dispatch_ready | D10: Update to loaded_and_dispatched | E10: Updated
A11: FF-010 | B11: Driver performance | C11: History exists | D11: Performance button | E11: Metrics shown
A12: FF-011 | B12: Vehicle inventory | C12: Loaded | D12: View inventory | E12: Quantities shown
A14: Total Tests | B14: =COUNTA(F2:F13)
A15: PASS | B15: =COUNTIF(F2:F13,"PASS")
A16: FAIL | B16: =COUNTIF(F2:F13,"FAIL")
A17: BLOCKED | B17: =COUNTIF(F2:F13,"BLOCKED")
A18: SKIPPED | B18: =COUNTIF(F2:F13,"SKIPPED")
A19: NOT TESTED | B19: =COUNTIF(F2:F13,"NOT TESTED")
A20: Pass Rate | B20: =IF(B15>0,B15/B14,0)

Sheet Settings Tests
A1: Test ID | B1: Test Case | C1: Precondition | D1: Steps | E1: Expected Result | F1: Pass/Fail | G1: Actual Result | H1: Notes
A2: FS-001 | B2: General - SLA hours | C2: Admin | D2: General > Critical=4h > Save | E2: Updated
A3: FS-002 | B3: GST - credentials | C3: Admin | D3: GST > Client ID, Secret, GSTIN > Save | E3: Saved
A4: FS-003 | B4: GST - enable | C4: Disabled | D4: Toggle on > Sandbox > Save | E4: Enabled
A5: FS-004 | B5: GST - disable | C5: Enabled | D5: Toggle off > Save | E5: Disabled
A6: FS-005 | B6: GST - mode change | C6: On | D6: Sandbox > Live > Save | E6: Changed
A7: FS-006 | B7: Prices - add | C7: Types exist | D7: New price > Save | E7: Added
A8: FS-007 | B8: Prices - edit | C8: Price exists | D8: Edit > Change > Save | E8: Updated
A9: FS-008 | B9: Thresholds - critical | C9: Types exist | D9: Critical=20 > Save | E9: Saved
A10: FS-009 | B10: Thresholds - warning | C10: Types exist | D10: Warning=50 > Save | E10: Saved
A11: FS-010 | B11: Users - create Finance | C11: Admin | D11: Add > Finance > Submit | E11: Created
A12: FS-011 | B12: Users - create Inventory | C12: Admin | D12: Add > Inventory > Submit | E12: Created
A13: FS-012 | B13: Users - create Driver | C13: Admin | D13: Add > Driver > Submit | E13: Created
... A18: FS-017 | B18: Billing - view | C18: Enabled | D18: Billing tab | E18: Summary shown
A20: Total Tests | B20: =COUNTA(F2:F19)
A21: PASS | B21: =COUNTIF(F2:F19,"PASS")
A22: FAIL | B22: =COUNTIF(F2:F19,"FAIL")
A23: BLOCKED | B23: =COUNTIF(F2:F19,"BLOCKED")
A24: SKIPPED | B24: =COUNTIF(F2:F19,"SKIPPED")
A25: NOT TESTED | B25: =COUNTIF(F2:F19,"NOT TESTED")
A26: Pass Rate | B26: =IF(B21>0,B21/B20,0)

Sheet Workflow - Order to Payment
A1: Test ID | B1: Workflow | C1: Step # | D1: Action | E1: Role | F1: Expected Result | G1: Pass/Fail | H1: Notes
A2: WF-001 | B2: Happy Path (GST OFF) | C2: 1 | D2: Login bhargava@gasagency.com | E2: DIST_ADMIN | F2: Login OK
A3: WF-002 | B3: Happy Path (GST OFF) | C3: 2 | D3: Create: Royal Kitchen, 19KG x 5, tomorrow | E3: DIST_ADMIN | F3: pending_driver_assignment
A4: WF-003 | B4: Happy Path (GST OFF) | C4: 3 | D4: Assign Raju + TS09-AB-1234 | E4: DIST_ADMIN | F4: pending_dispatch
A5: WF-004 | B5: Happy Path (GST OFF) | C5: 4 | D5: Confirm: 5 delivered, 3 empties | E5: DRIVER | F5: delivered
A6: WF-005 | B6: Happy Path (GST OFF) | C6: 5 | D6: Verify invoice: CGST=0, SGST=0, IGST=0 | E6: DIST_ADMIN | F6: Auto-created, no GST
A7: WF-006 | B7: Happy Path (GST OFF) | C7: 6 | D7: Download PDF | E7: DIST_ADMIN | F7: PDF OK
A8: WF-007 | B8: Happy Path (GST OFF) | C8: 7 | D8: Record full payment (cash) | E8: FINANCE | F8: Invoice paid
A9: WF-008 | B9: Happy Path (GST OFF) | C9: 8 | D9: Check ledger: debit+credit=0 | E9: FINANCE | F9: Balance 0
A10: WF-009 | B10: GST ON B2B Inter-state | C10: 1 | D10: Login sharma@gasdist.com | E10: DIST_ADMIN | F10: Login OK
A11: WF-010 | B11: GST ON B2B Inter-state | C11: 2 | D11: Order for inter-state B2B customer | E11: DIST_ADMIN | F11: Created
A12: WF-011 | B12: GST ON B2B Inter-state | C12: 3 | D12: Assign + deliver | E12: DIST_ADMIN | F12: Delivered
A13: WF-012 | B13: GST ON B2B Inter-state | C13: 4 | D13: Verify IGST only (CGST=0, SGST=0) | E13: DIST_ADMIN | F13: IGST > 0
... A48: WF-047 | B48: Vehicle Reconciliation | C48: 4 | D48: Assignment closed | E48: DIST_ADMIN | F48: Complete
A50: Total Tests | B50: =COUNTA(G2:G49)
A51: PASS | B51: =COUNTIF(G2:G49,"PASS")
A52: FAIL | B52: =COUNTIF(G2:G49,"FAIL")
A53: BLOCKED | B53: =COUNTIF(G2:G49,"BLOCKED")
A54: SKIPPED | B54: =COUNTIF(G2:G49,"SKIPPED")
A55: NOT TESTED | B55: =COUNTIF(G2:G49,"NOT TESTED")
A56: Pass Rate | B56: =IF(B51>0,B51/B50,0)

Sheet Workflow - Inventory Cycle
A1: Test ID | B1: Workflow | C1: Step # | D1: Action | E1: Role | F1: Expected Result | G1: Pass/Fail | H1: Notes
A2: IC-001 | B2: Daily Cycle | C2: 1 | D2: Note opening balance | E2: INVENTORY | F2: Opening=prev closing
A3: IC-002 | B3: Daily Cycle | C3: 2 | D3: Incoming: 19KG x 100 | E3: INVENTORY | F3: Stock increases
A4: IC-003 | B4: Daily Cycle | C4: 3 | D4: Create+dispatch orders | E4: DIST_ADMIN | F4: Vehicle loaded
A5: IC-004 | B5: Daily Cycle | C5: 4 | D5: Complete deliveries | E5: DRIVER | F5: Events created
A6: IC-005 | B6: Daily Cycle | C6: 5 | D6: Outgoing empties: 40 | E6: INVENTORY | F6: Returned
A7: IC-006 | B7: Daily Cycle | C7: 6 | D7: Verify closing | E7: INVENTORY | F7: Open+In-Del-Out
A8: IC-007 | B8: Daily Cycle | C8: 7 | D8: Lock day | E8: DIST_ADMIN | F8: Locked
A9: IC-008 | B9: Cancelled Stock | C9: 1 | D9: Order 10, deliver 7 | E9: DRIVER | F9: Cancelled=3
A10: IC-009 | B10: Cancelled Stock | C10: 2 | D10: Vehicle returns | E10: DRIVER | F10: Returned
A11: IC-010 | B11: Cancelled Stock | C11: 3 | D11: Return to depot | E11: INVENTORY | F11: returned_to_depot
A12: IC-011 | B12: Cancelled Stock | C12: 4 | D12: Reconcile | E12: INVENTORY | F12: Reconciled
A13: IC-012 | B13: Thresholds | C13: 1 | D13: Set critical=20 | E13: DIST_ADMIN | F13: Saved
... A15: IC-014 | B15: Thresholds | C15: 3 | D15: Warning=50, stock 20-50 | E15: DIST_ADMIN | F15: Warning badge
A17: Total Tests | B17: =COUNTA(G2:G16)
A18: PASS | B18: =COUNTIF(G2:G16,"PASS")
A19: FAIL | B19: =COUNTIF(G2:G16,"FAIL")
A20: BLOCKED | B20: =COUNTIF(G2:G16,"BLOCKED")
A21: SKIPPED | B21: =COUNTIF(G2:G16,"SKIPPED")
A22: NOT TESTED | B22: =COUNTIF(G2:G16,"NOT TESTED")
A23: Pass Rate | B23: =IF(B18>0,B18/B17,0)

Sheet Customer Portal Tests
A1: Test ID | B1: Test Case | C1: Precondition | D1: Steps | E1: Expected Result | F1: Pass/Fail | G1: Actual Result | H1: Notes
A2: CP-001 | B2: Login | C2: Portal provisioned | D2: Enter creds > Submit | E2: Dashboard shown
A3: CP-002 | B3: Dashboard KPIs | C3: Logged in | D3: Check KPIs | E3: Orders, Invoices, Outstanding
A4: CP-003 | B4: Recent orders | C4: Has orders | D4: Check section | E4: Up to 5 shown
A5: CP-004 | B5: Place order | C5: Logged in | D5: Create > 19KG x 3 > Submit | E5: Placed
A6: CP-005 | B6: Order validation | C6: Logged in | D6: Submit empty | E6: Error
A7: CP-006 | B7: Orders list | C7: Has orders | D7: Orders page | E7: List with status
A8: CP-007 | B8: Order detail | C8: Order exists | D8: Click order | E8: Full detail
A9: CP-008 | B9: Invoices list | C9: Has invoices | D9: Invoices page | E9: List shown
A10: CP-009 | B10: Invoice detail | C10: Invoice exists | D10: Click invoice | E10: Line items, GST
A11: CP-010 | B11: Download invoice | C11: Invoice exists | D11: Download | E11: PDF OK
A12: CP-011 | B12: Payments list | C12: Has payments | D12: Payments page | E12: List shown
A13: CP-012 | B13: Account balance | C13: Transactions | D13: Balance page | E13: Outstanding shown
... A19: CP-018 | B19: Invoice filter | C19: Various | D19: Status filter | E19: Filtered
A21: Total Tests | B21: =COUNTA(F2:F20)
A22: PASS | B22: =COUNTIF(F2:F20,"PASS")
A23: FAIL | B23: =COUNTIF(F2:F20,"FAIL")
A24: BLOCKED | B24: =COUNTIF(F2:F20,"BLOCKED")
A25: SKIPPED | B25: =COUNTIF(F2:F20,"SKIPPED")
A26: NOT TESTED | B26: =COUNTIF(F2:F20,"NOT TESTED")
A27: Pass Rate | B27: =IF(B22>0,B22/B21,0)

Sheet Negative & Edge Cases
A1: Test ID | B1: Test Case | C1: Category | D1: Steps | E1: Expected Result | F1: Pass/Fail | G1: Actual Result | H1: Notes
A2: NE-001 | B2: Wrong password | C2: Auth | D2: Valid email + wrong pw | E2: Invalid credentials
A3: NE-002 | B3: Non-existent email | C3: Auth | D3: Fake email | E3: Invalid credentials
A4: NE-003 | B4: Empty login fields | C4: Auth | D4: Submit empty | E4: Validation errors
A5: NE-004 | B5: Suspended user | C5: Auth | D5: Login as suspended | E5: Inactive
A6: NE-005 | B6: Admin page as Customer | C6: AuthZ | D6: Customer > /app/orders | E6: Denied
A7: NE-006 | B7: Portal as Admin | C7: AuthZ | D7: Admin > /app/customer/dashboard | E7: Denied
A8: NE-007 | B8: Expired token | C8: Auth | D8: Use expired JWT | E8: 401
A9: NE-008 | B9: Invalid token | C9: Auth | D9: Garbage JWT | E9: 401
A10: NE-009 | B10: Stopped customer order | C10: Business | D10: Order for stopped customer | E10: Error
A11: NE-010 | B11: Deliver > ordered | C11: Business | D11: Order 5, deliver 10 | E11: Error
A12: NE-011 | B12: Double delivery | C12: Business | D12: Confirm twice | E12: Error
A13: NE-012 | B13: Overpayment | C13: Business | D13: Pay more than invoice | E13: Excess unallocated
... A31: NE-030 | B31: Concurrent edit | C31: Concurrency | D31: 2 tabs same order | E31: Conflict handled
A33: Total Tests | B33: =COUNTA(F2:F32)
A34: PASS | B34: =COUNTIF(F2:F32,"PASS")
A35: FAIL | B35: =COUNTIF(F2:F32,"FAIL")
A36: BLOCKED | B36: =COUNTIF(F2:F32,"BLOCKED")
A37: SKIPPED | B37: =COUNTIF(F2:F32,"SKIPPED")
A38: NOT TESTED | B38: =COUNTIF(F2:F32,"NOT TESTED")
A39: Pass Rate | B39: =IF(B34>0,B34/B33,0)

Sheet Summary Dashboard
A1: Sheet | B1: Total Tests | C1: PASS | D1: FAIL | E1: BLOCKED | F1: SKIPPED | G1: NOT TESTED | H1: Pass Rate
A2: Role-Based Access | B2: =COUNTA('Role-Based Access'!F2:F53) | C2: =COUNTIF('Role-Based Access'!F2:F53,"PASS") | D2: =COUNTIF('Role-Based Access'!F2:F53,"FAIL") | E2: =COUNTIF('Role-Based Access'!F2:F53,"BLOCKED") | F2: =COUNTIF('Role-Based Access'!F2:F53,"SKIPPED") | G2: =COUNTIF('Role-Based Access'!F2:F53,"NOT TESTED") | H2: =IF(B2>0,C2/B2,0)
A3: Orders Tests | B3: =COUNTA('Orders Tests'!F2:F23) | C3: =COUNTIF('Orders Tests'!F2:F23,"PASS") | D3: =COUNTIF('Orders Tests'!F2:F23,"FAIL") | E3: =COUNTIF('Orders Tests'!F2:F23,"BLOCKED") | F3: =COUNTIF('Orders Tests'!F2:F23,"SKIPPED") | G3: =COUNTIF('Orders Tests'!F2:F23,"NOT TESTED") | H3: =IF(B3>0,C3/B3,0)
A4: Inventory Tests | B4: =COUNTA('Inventory Tests'!F2:F19) | C4: =COUNTIF('Inventory Tests'!F2:F19,"PASS") | D4: =COUNTIF('Inventory Tests'!F2:F19,"FAIL") | E4: =COUNTIF('Inventory Tests'!F2:F19,"BLOCKED") | F4: =COUNTIF('Inventory Tests'!F2:F19,"SKIPPED") | G4: =COUNTIF('Inventory Tests'!F2:F19,"NOT TESTED") | H4: =IF(B4>0,C4/B4,0)
A5: Customer Tests | B5: =COUNTA('Customer Tests'!F2:F18) | C5: =COUNTIF('Customer Tests'!F2:F18,"PASS") | D5: =COUNTIF('Customer Tests'!F2:F18,"FAIL") | E5: =COUNTIF('Customer Tests'!F2:F18,"BLOCKED") | F5: =COUNTIF('Customer Tests'!F2:F18,"SKIPPED") | G5: =COUNTIF('Customer Tests'!F2:F18,"NOT TESTED") | H5: =IF(B5>0,C5/B5,0)
A6: Billing Tests | B6: =COUNTA('Billing Tests'!F2:F27) | C6: =COUNTIF('Billing Tests'!F2:F27,"PASS") | D6: =COUNTIF('Billing Tests'!F2:F27,"FAIL") | E6: =COUNTIF('Billing Tests'!F2:F27,"BLOCKED") | F6: =COUNTIF('Billing Tests'!F2:F27,"SKIPPED") | G6: =COUNTIF('Billing Tests'!F2:F27,"NOT TESTED") | H6: =IF(B6>0,C6/B6,0)
A7: Fleet Tests | B7: =COUNTA('Fleet Tests'!F2:F12) | C7: =COUNTIF('Fleet Tests'!F2:F12,"PASS") | D7: =COUNTIF('Fleet Tests'!F2:F12,"FAIL") | E7: =COUNTIF('Fleet Tests'!F2:F12,"BLOCKED") | F7: =COUNTIF('Fleet Tests'!F2:F12,"SKIPPED") | G7: =COUNTIF('Fleet Tests'!F2:F12,"NOT TESTED") | H7: =IF(B7>0,C7/B7,0)
A8: Settings Tests | B8: =COUNTA('Settings Tests'!F2:F18) | C8: =COUNTIF('Settings Tests'!F2:F18,"PASS") | D8: =COUNTIF('Settings Tests'!F2:F18,"FAIL") | E8: =COUNTIF('Settings Tests'!F2:F18,"BLOCKED") | F8: =COUNTIF('Settings Tests'!F2:F18,"SKIPPED") | G8: =COUNTIF('Settings Tests'!F2:F18,"NOT TESTED") | H8: =IF(B8>0,C8/B8,0)
A9: Workflow - Order to Payment | B9: =COUNTA('Workflow - Order to Payment'!G2:G48) | C9: =COUNTIF('Workflow - Order to Payment'!G2:G48,"PASS") | D9: =COUNTIF('Workflow - Order to Payment'!G2:G48,"FAIL") | E9: =COUNTIF('Workflow - Order to Payment'!G2:G48,"BLOCKED") | F9: =COUNTIF('Workflow - Order to Payment'!G2:G48,"SKIPPED") | G9: =COUNTIF('Workflow - Order to Payment'!G2:G48,"NOT TESTED") | H9: =IF(B9>0,C9/B9,0)
A10: Workflow - Inventory Cycle | B10: =COUNTA('Workflow - Inventory Cycle'!G2:G15) | C10: =COUNTIF('Workflow - Inventory Cycle'!G2:G15,"PASS") | D10: =COUNTIF('Workflow - Inventory Cycle'!G2:G15,"FAIL") | E10: =COUNTIF('Workflow - Inventory Cycle'!G2:G15,"BLOCKED") | F10: =COUNTIF('Workflow - Inventory Cycle'!G2:G15,"SKIPPED") | G10: =COUNTIF('Workflow - Inventory Cycle'!G2:G15,"NOT TESTED") | H10: =IF(B10>0,C10/B10,0)
A11: Customer Portal Tests | B11: =COUNTA('Customer Portal Tests'!F2:F19) | C11: =COUNTIF('Customer Portal Tests'!F2:F19,"PASS") | D11: =COUNTIF('Customer Portal Tests'!F2:F19,"FAIL") | E11: =COUNTIF('Customer Portal Tests'!F2:F19,"BLOCKED") | F11: =COUNTIF('Customer Portal Tests'!F2:F19,"SKIPPED") | G11: =COUNTIF('Customer Portal Tests'!F2:F19,"NOT TESTED") | H11: =IF(B11>0,C11/B11,0)
A12: Negative & Edge Cases | B12: =COUNTA('Negative & Edge Cases'!F2:F31) | C12: =COUNTIF('Negative & Edge Cases'!F2:F31,"PASS") | D12: =COUNTIF('Negative & Edge Cases'!F2:F31,"FAIL") | E12: =COUNTIF('Negative & Edge Cases'!F2:F31,"BLOCKED") | F12: =COUNTIF('Negative & Edge Cases'!F2:F31,"SKIPPED") | G12: =COUNTIF('Negative & Edge Cases'!F2:F31,"NOT TESTED") | H12: =IF(B12>0,C12/B12,0)
A14: GRAND TOTAL | B14: =SUM(B2:B12) | C14: =SUM(C2:C12) | D14: =SUM(D2:D12) | E14: =SUM(E2:E12) | F14: =SUM(F2:F12) | G14: =SUM(G2:G12) | H14: =IF(B14>0,C14/B14,0)
A16: OVERALL STATUS
A17: =IF(D14=0,IF(C14=B14,"ALL PASSED","IN PROGRESS"),"FAILURES FOUND")
